slack_channeler/__init__.py
slack_channeler/cli.py
slack_channeler/server.py
slack_channeler/version.py
slack_channeler-0.0.1.dev0.dist-info/entry_points.txt
slack_channeler-0.0.1.dev0.dist-info/LICENSE
slack_channeler-0.0.1.dev0.dist-info/WHEEL
slack_channeler-0.0.1.dev0.dist-info/METADATA
slack_channeler-0.0.1.dev0.dist-info/RECORD
