Metadata-Version: 2.1
Name: slack-channeler
Version: 0.0.1.dev0
Summary: Power a Slack bot with Django Channels v2
License: MIT
Author: Zach "theY4Kman" Kanzler
Author-email: they4kman@gmail.com
Requires-Python: >=3.6
Classifier: License :: OSI Approved :: MIT License
Classifier: Programming Language :: Python :: 3
Classifier: Programming Language :: Python :: 3.6
Classifier: Programming Language :: Python :: 3.7
Requires-Dist: channels (>=2.2,<3.0)
Requires-Dist: click (>=7.0,<8.0)
Requires-Dist: slackclient (>=2.0,<3.0)
